acti_motus/__init__.py
acti_motus/activities.py
acti_motus/calibration.py
acti_motus/exposures.py
acti_motus/features.py
acti_motus/iterators.py
acti_motus/py.typed
acti_motus/sens_parser.py
acti_motus/settings.py
acti_motus/classifications/__init__.py
acti_motus/classifications/arm.py
acti_motus/classifications/calf.py
acti_motus/classifications/references.py
acti_motus/classifications/sensor.py
acti_motus/classifications/thigh.py
acti_motus/classifications/trunk.py
acti_motus-2.2.0.dist-info/METADATA
acti_motus-2.2.0.dist-info/WHEEL
acti_motus-2.2.0.dist-info/licenses/LICENSE
acti_motus-2.2.0.dist-info/RECORD
