Metadata-Version: 2.4
Name: acti-motus
Version: 2.2.0
Summary: Python-powered activity detection algorithms that build upon Acti4, processing data from multiple accelerometers with a required thigh sensor.
Project-URL: Homepage, https://github.com/acti-motus/acti-motus
Project-URL: Documentation, https://github.com/acti-motus/acti-motus
Project-URL: Source, https://github.com/acti-motus/acti-motus
Project-URL: Changelog, https://github.com/acti-motus/acti-motus/blob/main/CHANGELOG.md
Author-email: Josef Heidler <heidlerjosef@gmail.com>, Jon Roslyng Larsen <xjla@nfa.dk>, Sebastian Asmussen Sode Hørlück <ssh@nfa.dk>
License-Expression: BSD-3-Clause
License-File: LICENSE
Keywords: accelerometers,activity-classification,movement-behavior
Classifier: Intended Audience :: Education
Classifier: Intended Audience :: Science/Research
Classifier: Operating System :: OS Independent
Classifier: Programming Language :: Python
Classifier: Programming Language :: Python :: 3
Classifier: Programming Language :: Python :: 3 :: Only
Classifier: Programming Language :: Python :: 3.11
Classifier: Programming Language :: Python :: 3.12
Classifier: Topic :: Scientific/Engineering
Requires-Python: >=3.11
Requires-Dist: numpy>=2.2.6
Requires-Dist: pandas>=2.2.3
Requires-Dist: pyarrow>=20.0.0
Requires-Dist: scikit-digital-health>=0.17.9
